{
  "name": "Default Scene",
  "program_number": 0,
  "send_pc_on_change": true,
  "touchwheel_mode": "buttons",
  "touchpads": [
    {
      "enabled": true,
      "actions": [
        {
          "type": 4,
          "cc": 1,
          "value": 127
        }
      ]
    },
    {
      "enabled": true,
      "actions": [
        {
          "type": 4,
          "cc": 2,
          "value": 127
        }
      ]
    },
    {
      "enabled": true,
      "actions": [
        {
          "type": 4,
          "cc": 3,
          "value": 127
        }
      ]
    },
    {
      "enabled": true,
      "actions": [
        {
          "type": 4,
          "cc": 4,
          "value": 127
        }
      ]
    },
    {
      "enabled": true,
      "actions": [
        {
          "type": 4,
          "cc": 5,
          "value": 127
        }
      ]
    },
    {
      "enabled": true,
      "actions": [
        {
          "type": 4,
          "cc": 6,
          "value": 127
        }
      ]
    },
    {
      "enabled": true,
      "actions": [
        {
          "type": 4,
          "cc": 7,
          "value": 127
        }
      ]
    },
    {
      "enabled": true,
      "actions": [
        {
          "type": 4,
          "cc": 8,
          "value": 127
        }
      ]
    },
    {
      "enabled": true,
      "actions": [
        {
          "type": 4,
          "cc": 9,
          "value": 127
        }
      ]
    },
    {
      "enabled": true,
      "actions": [
        {
          "type": 4,
          "cc": 10,
          "value": 127
        }
      ]
    },
    {
      "enabled": true,
      "actions": [
        {
          "type": 4,
          "cc": 11,
          "value": 127
        }
      ]
    },
    {
      "enabled": true,
      "actions": [
        {
          "type": 4,
          "cc": 12,
          "value": 127
        }
      ]
    }
  ],
  "button_left": [
    {
      "type": 1
    }
  ],
  "button_right": [
    {
      "type": 0
    }
  ],
  "button_both": [
    {
      "type": 24
    }
  ],
  "expression": {
    "enabled": true,
    "cc_number": 4,
    "curve_type": 0,
    "polarity": 0,
    "min_value": 0,
    "max_value": 127
  },
  "cv": {
    "enabled": true,
    "cc_number": 16,
    "curve_type": 0,
    "polarity": 0,
    "min_value": 0,
    "max_value": 127
  },
  "proximity": {
    "enabled": true,
    "cc_number": 17,
    "curve_type": 0,
    "polarity": 1,
    "min_value": 0,
    "max_value": 127,
    "use_idle_value": true,
    "idle_value": 64,
    "idle_timeout_ms": 1000
  },
  "als": {
    "enabled": true,
    "cc_number": 18,
    "curve_type": 0,
    "polarity": 0,
    "min_value": 0,
    "max_value": 127
  }
}

